eunits/__init__.py
EUnits-0.0.3.dist-info/LICENSE
EUnits-0.0.3.dist-info/METADATA
EUnits-0.0.3.dist-info/WHEEL
EUnits-0.0.3.dist-info/top_level.txt
EUnits-0.0.3.dist-info/RECORD
